{
  "id": "76a2b7d1-98ef-42a3-8aef-a5e22087324e",
  "name": "source",
  "isOverridable": true,
  "entries": [
    {
      "value": "BBC",
      "synonyms": [
        "BBC"
      ]
    },
    {
      "value": "CNN",
      "synonyms": [
        "CNN"
      ]
    },
    {
      "value": "NPR",
      "synonyms": [
        "NPR"
      ]
    },
    {
      "value": "ABC",
      "synonyms": [
        "ABC"
      ]
    },
    {
      "value": "Washington Post",
      "synonyms": [
        "Washington Post"
      ]
    },
    {
      "value": "New York Times",
      "synonyms": [
        "New York Times",
        "The New York Times",
        "NY Times",
        "The NY Times"
      ]
    },
    {
      "value": "Google News",
      "synonyms": [
        "Google News"
      ]
    },
    {
      "value": "Yahoo",
      "synonyms": [
        "Yahoo"
      ]
    },
    {
      "value": "Twitter",
      "synonyms": [
        "Twitter"
      ]
    },
    {
      "value": "Facebook",
      "synonyms": [
        "Facebook"
      ]
    }
  ],
  "isEnum": false,
  "automatedExpansion": true
}